empathi/embeddings.py
empathi/empathi.py
empathi-1.0.6.dist-info/METADATA
empathi-1.0.6.dist-info/WHEEL
empathi-1.0.6.dist-info/entry_points.txt
empathi-1.0.6.dist-info/licenses/LICENSE
empathi-1.0.6.dist-info/RECORD
