Metadata-Version: 2.4
Name: empathi
Version: 1.0.6
Summary: An embedding-based phage protein annotation tool by hierarchical assignment
Project-URL: Homepage, https://huggingface.co/AlexandreBoulay/EmPATHi
Author: Alexandre Boulay, Clovis Galiez, Elsa Rousseau
Author-email: Alexandre Boulay <alexandre.boulay.6@ulaval.ca>
License-File: LICENSE
Keywords: bacteriophages,bioinformatics,phages,protein functions
Classifier: License :: OSI Approved :: GNU General Public License v3 (GPLv3)
Classifier: Programming Language :: Python :: 3
Requires-Python: >=3.11.5
Requires-Dist: joblib==1.2.0
Requires-Dist: numpy==1.26.4
Requires-Dist: pandas==2.2.1
Requires-Dist: scikit-learn==1.5.0
Requires-Dist: scipy==1.13.1
Requires-Dist: sentencepiece==0.2.0
Requires-Dist: torch==2.3.0
Requires-Dist: transformers==4.43.1
